{
  "ret": true,
  "data": {
    "sightName": "广州长隆旅游度假区(AAAAA景区)",
    "bannerImg": "http://img1.qunarzz.com/sight/p0/1603/3b/3bd311262ee06d8c90.img.jpg_600x330_cd2e3bf7.jpg",
    "gallaryImgs": ["http://img1.qunarzz.com/sight/p0/1603/3b/3bd311262ee06d8c90.img.jpg_r_800x800_41637b9b.jpg", "http://img1.qunarzz.com/sight/p0/1603/3b/3bd311262ee06d8c90.img.jpg_r_800x800_41637b9b.jpg"],
    "categoryList": [{
        "title": "成人票",
        "children": [{
          "title": "成人三馆联票",
          "children": [{
            "title": "成人三馆联票 - 某一连锁店销售"
          }]
        },{
          "title": "成人五馆联票"
        }]
      }, {
        "title": "学生票"
      }, {
        "title": "儿童票"
      }, {
        "title": "特惠票"
      }]
  }
}
